{
  "generated_at": "2026-06-07T06:00:00-05:00",
  "window_start": "2026-06-06T06:00:00-05:00",
  "window_end": "2026-06-07T06:00:00-05:00",
  "source_workspace": "Chick-fil-A Brenham",
  "excluded_channels": ["general"],
  "standup_summary": "*☀️ Morning Standup*\nRecipient: Cody\nDate: June 7, 2026\nOverall Status: 🟡 Attention Needed\nOperations were mostly stable yesterday, but one reporting issue needs follow-up today. Primary focus is confirming shortage reporting is capturing every submitted employee.\n\n*🔥 Priority Items*\n• Investigate why shortage tracking only sent Destiny when multiple people were entered.\n• Confirm the original submission data and workflow execution path match the posted Slack report.\n\n*📈 Operational Highlights*\n*Operations*\n• Reviewed the app and operations issue tied to shortage reporting output.\n\n*👤 Your Activity*\n*You Completed*\n• Reviewed the shortage reporting issue and narrowed the problem to message output versus submission intent.\n\n*Awaiting Your Response*\n• Decide whether to correct the reporting logic or rerun the affected submission after validation.\n\n*Mentions*\n• None.\n\n*⚠️ Watch Items*\n• Shortage reporting may be dropping employees when multiple names are submitted in one event.\n\n*🎯 Today's Focus*\n• Pull the original submission payload and compare it against the Slack message body.\n• Review the relevant n8n execution logs before making any workflow change.\n• Confirm whether this is a parsing issue or a downstream formatting issue.\n\n*✅ Wins*\n• The issue was isolated quickly enough to investigate before it repeated.",
  "todoist_tasks": [
    {
      "title": "Investigate shortage tracking only sending Destiny",
      "summary": "Itzel entered multiple drawer shortages, but only Destiny appeared in the Slack report.",
      "blocker": "May need source submission data or n8n execution logs.",
      "due_string": "today",
      "priority": 2,
      "source": {
        "channel_id": "C06JVBVMBPV",
        "channel_name": "cash-managment",
        "message_ts": "1780807991.680299",
        "thread_ts": "1780807991.680299",
        "permalink": "https://chick-fil-abrenham.slack.com/archives/C06JVBVMBPV/p1780807991680299"
      }
    }
  ]
}
